thingsboardlink/__init__.py
thingsboardlink/client.py
thingsboardlink/exceptions.py
thingsboardlink/models.py
thingsboardlink/services/__init__.py
thingsboardlink/services/alarm_service.py
thingsboardlink/services/attribute_service.py
thingsboardlink/services/device_service.py
thingsboardlink/services/relation_service.py
thingsboardlink/services/rpc_service.py
thingsboardlink/services/telemetry_service.py
thingsboardlink-1.2.0.dist-info/licenses/LICENSE.txt
thingsboardlink-1.2.0.dist-info/METADATA
thingsboardlink-1.2.0.dist-info/WHEEL
thingsboardlink-1.2.0.dist-info/top_level.txt
thingsboardlink-1.2.0.dist-info/RECORD
